{
  "version": 1,
  "physics_tps": 60,
  "result": "Individual collision render demo",
  "seed": "12345",
  "duration_ticks": 700,
  "orders": [
    {
      "tick": 6,
      "units": [
        1
      ],
      "x": 650.0,
      "y": 700.0,
      "target": 6
    }
  ],
  "camera": [
    {
      "tick": 0,
      "x": 650.0,
      "y": 500.0,
      "zoom": 1.3
    },
    {
      "tick": 3,
      "x": 650.0,
      "y": 500.0,
      "zoom": 1.3
    },
    {
      "tick": 6,
      "x": 650.0,
      "y": 500.0,
      "zoom": 1.3
    },
    {
      "tick": 9,
      "x": 650.0,
      "y": 500.0,
      "zoom": 1.3
    },
    {
      "tick": 12,
      "x": 650.0,
      "y": 500.0,
      "zoom": 1.3
    },
    {
      "tick": 15,
      "x": 650.0,
      "y": 500.0,
      "zoom": 1.3
    },
    {
      "tick": 18,
      "x": 650.0,
      "y": 500.0,
      "zoom": 1.3
    },
    {
      "tick": 21,
      "x": 650.0,
      "y": 500.0,
      "zoom": 1.3
    },
    {
      "tick": 24,
      "x": 650.0,
      "y": 500.0,
      "zoom": 1.3
    },
    {
      "tick": 27,
      "x": 650.0,
      "y": 500.0,
      "zoom": 1.3
    },
    {
      "tick": 30,
      "x": 650.0,
      "y": 500.0,
      "zoom": 1.3
    },
    {
      "tick": 33,
      "x": 650.0,
      "y": 500.0,
      "zoom": 1.3
    },
    {
      "tick": 36,
      "x": 650.0,
      "y": 500.0,
      "zoom": 1.3
    },
    {
      "tick": 39,
      "x": 650.0,
      "y": 500.0,
      "zoom": 1.3
    },
    {
      "tick": 42,
      "x": 650.0,
      "y": 500.0,
      "zoom": 1.3
    },
    {
      "tick": 45,
      "x": 650.0,
      "y": 500.0,
      "zoom": 1.3
    },
    {
      "tick": 48,
      "x": 650.0,
      "y": 500.0,
      "zoom": 1.3
    },
    {
      "tick": 51,
      "x": 650.0,
      "y": 500.0,
      "zoom": 1.3
    },
    {
      "tick": 54,
      "x": 650.0,
      "y": 500.0,
      "zoom": 1.3
    },
    {
      "tick": 57,
      "x": 650.0,
      "y": 500.0,
      "zoom": 1.3
    },
    {
      "tick": 60,
      "x": 650.0,
      "y": 500.0,
      "zoom": 1.3
    },
    {
      "tick": 63,
      "x": 650.0,
      "y": 500.0,
      "zoom": 1.3
    },
    {
      "tick": 66,
      "x": 650.0,
      "y": 500.0,
      "zoom": 1.3
    },
    {
      "tick": 69,
      "x": 650.0,
      "y": 500.0,
      "zoom": 1.3
    },
    {
      "tick": 72,
      "x": 650.0,
      "y": 500.0,
      "zoom": 1.3
    },
    {
      "tick": 75,
      "x": 650.0,
      "y": 500.0,
      "zoom": 1.3
    },
    {
      "tick": 78,
      "x": 650.0,
      "y": 500.0,
      "zoom": 1.3
    },
    {
      "tick": 81,
      "x": 650.0,
      "y": 500.0,
      "zoom": 1.3
    },
    {
      "tick": 84,
      "x": 650.0,
      "y": 500.0,
      "zoom": 1.3
    },
    {
      "tick": 87,
      "x": 650.0,
      "y": 500.0,
      "zoom": 1.3
    },
    {
      "tick": 90,
      "x": 650.0,
      "y": 500.0,
      "zoom": 1.3
    },
    {
      "tick": 93,
      "x": 650.0,
      "y": 500.0,
      "zoom": 1.3024
    },
    {
      "tick": 96,
      "x": 650.0,
      "y": 500.0,
      "zoom": 1.3097
    },
    {
      "tick": 99,
      "x": 650.0,
      "y": 500.0,
      "zoom": 1.3215
    },
    {
      "tick": 102,
      "x": 650.0,
      "y": 500.0,
      "zoom": 1.3378
    },
    {
      "tick": 105,
      "x": 650.0,
      "y": 500.0,
      "zoom": 1.3585
    },
    {
      "tick": 108,
      "x": 650.0,
      "y": 500.0,
      "zoom": 1.3832
    },
    {
      "tick": 111,
      "x": 650.0,
      "y": 500.0,
      "zoom": 1.412
    },
    {
      "tick": 114,
      "x": 650.0,
      "y": 500.0,
      "zoom": 1.4447
    },
    {
      "tick": 117,
      "x": 650.0,
      "y": 500.0,
      "zoom": 1.481
    },
    {
      "tick": 120,
      "x": 650.0,
      "y": 500.0,
      "zoom": 1.5208
    },
    {
      "tick": 123,
      "x": 650.0,
      "y": 500.0,
      "zoom": 1.5641
    },
    {
      "tick": 126,
      "x": 650.0,
      "y": 500.0,
      "zoom": 1.6105
    },
    {
      "tick": 129,
      "x": 650.0,
      "y": 500.0,
      "zoom": 1.66
    },
    {
      "tick": 132,
      "x": 650.0,
      "y": 500.0,
      "zoom": 1.7125
    },
    {
      "tick": 135,
      "x": 650.0,
      "y": 500.0,
      "zoom": 1.7676
    },
    {
      "tick": 138,
      "x": 650.0,
      "y": 500.0,
      "zoom": 1.8254
    },
    {
      "tick": 141,
      "x": 650.0,
      "y": 500.0,
      "zoom": 1.8857
    },
    {
      "tick": 144,
      "x": 650.0,
      "y": 500.0,
      "zoom": 1.9482
    },
    {
      "tick": 147,
      "x": 650.0,
      "y": 500.0,
      "zoom": 2.0128
    },
    {
      "tick": 150,
      "x": 650.0,
      "y": 500.0,
      "zoom": 2.0794
    },
    {
      "tick": 153,
      "x": 650.0,
      "y": 500.0,
      "zoom": 2.1478
    },
    {
      "tick": 156,
      "x": 650.0,
      "y": 500.0,
      "zoom": 2.2179
    },
    {
      "tick": 159,
      "x": 650.0,
      "y": 500.0,
      "zoom": 2.2895
    },
    {
      "tick": 162,
      "x": 650.0,
      "y": 500.0,
      "zoom": 2.3625
    },
    {
      "tick": 165,
      "x": 650.0,
      "y": 500.0,
      "zoom": 2.4366
    },
    {
      "tick": 168,
      "x": 650.0,
      "y": 500.0,
      "zoom": 2.5118
    },
    {
      "tick": 171,
      "x": 650.0,
      "y": 500.0,
      "zoom": 2.5879
    },
    {
      "tick": 174,
      "x": 650.0,
      "y": 500.0,
      "zoom": 2.6647
    },
    {
      "tick": 177,
      "x": 650.0,
      "y": 500.0,
      "zoom": 2.7421
    },
    {
      "tick": 180,
      "x": 650.0,
      "y": 500.0,
      "zoom": 2.8199
    },
    {
      "tick": 183,
      "x": 650.0,
      "y": 500.0,
      "zoom": 2.8979
    },
    {
      "tick": 186,
      "x": 650.0,
      "y": 500.0,
      "zoom": 2.9761
    },
    {
      "tick": 189,
      "x": 650.0,
      "y": 500.0,
      "zoom": 3.0541
    },
    {
      "tick": 192,
      "x": 650.0,
      "y": 500.0,
      "zoom": 3.132
    },
    {
      "tick": 195,
      "x": 650.0,
      "y": 500.0,
      "zoom": 3.2096
    },
    {
      "tick": 198,
      "x": 650.0,
      "y": 500.0,
      "zoom": 3.2866
    },
    {
      "tick": 201,
      "x": 650.0,
      "y": 500.0,
      "zoom": 3.3629
    },
    {
      "tick": 204,
      "x": 650.0,
      "y": 500.0,
      "zoom": 3.4384
    },
    {
      "tick": 207,
      "x": 650.0,
      "y": 500.0,
      "zoom": 3.5129
    },
    {
      "tick": 210,
      "x": 650.0,
      "y": 500.0,
      "zoom": 3.5863
    },
    {
      "tick": 213,
      "x": 650.0,
      "y": 500.0,
      "zoom": 3.6584
    },
    {
      "tick": 216,
      "x": 650.0,
      "y": 500.0,
      "zoom": 3.729
    },
    {
      "tick": 219,
      "x": 650.0,
      "y": 500.0,
      "zoom": 3.798
    },
    {
      "tick": 222,
      "x": 650.0,
      "y": 500.0,
      "zoom": 3.8652
    },
    {
      "tick": 225,
      "x": 650.0,
      "y": 500.0,
      "zoom": 3.9305
    },
    {
      "tick": 228,
      "x": 650.0,
      "y": 500.0,
      "zoom": 3.9938
    },
    {
      "tick": 231,
      "x": 650.0,
      "y": 500.0,
      "zoom": 4.0548
    },
    {
      "tick": 234,
      "x": 650.0,
      "y": 500.0,
      "zoom": 4.1134
    },
    {
      "tick": 237,
      "x": 650.0,
      "y": 500.0,
      "zoom": 4.1694
    },
    {
      "tick": 240,
      "x": 650.0,
      "y": 500.0,
      "zoom": 4.2228
    },
    {
      "tick": 243,
      "x": 650.0,
      "y": 500.0,
      "zoom": 4.2733
    },
    {
      "tick": 246,
      "x": 650.0,
      "y": 500.0,
      "zoom": 4.3208
    },
    {
      "tick": 249,
      "x": 650.0,
      "y": 500.0,
      "zoom": 4.3651
    },
    {
      "tick": 252,
      "x": 650.0,
      "y": 500.0,
      "zoom": 4.4061
    },
    {
      "tick": 255,
      "x": 650.0,
      "y": 500.0,
      "zoom": 4.4436
    },
    {
      "tick": 258,
      "x": 650.0,
      "y": 500.0,
      "zoom": 4.4775
    },
    {
      "tick": 261,
      "x": 650.0,
      "y": 500.0,
      "zoom": 4.5076
    },
    {
      "tick": 264,
      "x": 650.0,
      "y": 500.0,
      "zoom": 4.5337
    },
    {
      "tick": 267,
      "x": 650.0,
      "y": 500.0,
      "zoom": 4.5558
    },
    {
      "tick": 270,
      "x": 650.0,
      "y": 500.0,
      "zoom": 4.5735
    },
    {
      "tick": 273,
      "x": 650.0,
      "y": 500.0,
      "zoom": 4.5869
    },
    {
      "tick": 276,
      "x": 650.0,
      "y": 500.0,
      "zoom": 4.5957
    },
    {
      "tick": 279,
      "x": 650.0,
      "y": 500.0,
      "zoom": 4.5997
    },
    {
      "tick": 282,
      "x": 650.0,
      "y": 500.0,
      "zoom": 4.6
    },
    {
      "tick": 285,
      "x": 650.0,
      "y": 500.0,
      "zoom": 4.6
    },
    {
      "tick": 288,
      "x": 650.0,
      "y": 500.0,
      "zoom": 4.6
    },
    {
      "tick": 291,
      "x": 650.0,
      "y": 500.0,
      "zoom": 4.6
    },
    {
      "tick": 294,
      "x": 650.0,
      "y": 500.0,
      "zoom": 4.6
    },
    {
      "tick": 297,
      "x": 650.0,
      "y": 500.0,
      "zoom": 4.6
    },
    {
      "tick": 300,
      "x": 650.0,
      "y": 500.0,
      "zoom": 4.6
    },
    {
      "tick": 303,
      "x": 650.0,
      "y": 500.0,
      "zoom": 4.6
    },
    {
      "tick": 306,
      "x": 650.0,
      "y": 500.0,
      "zoom": 4.6
    },
    {
      "tick": 309,
      "x": 650.0,
      "y": 500.0,
      "zoom": 4.6
    },
    {
      "tick": 312,
      "x": 650.0,
      "y": 500.0,
      "zoom": 4.6
    },
    {
      "tick": 315,
      "x": 650.0,
      "y": 500.0,
      "zoom": 4.6
    },
    {
      "tick": 318,
      "x": 650.0,
      "y": 500.0,
      "zoom": 4.6
    },
    {
      "tick": 321,
      "x": 650.0,
      "y": 500.0,
      "zoom": 4.6
    },
    {
      "tick": 324,
      "x": 650.0,
      "y": 500.0,
      "zoom": 4.6
    },
    {
      "tick": 327,
      "x": 650.0,
      "y": 500.0,
      "zoom": 4.6
    },
    {
      "tick": 330,
      "x": 650.0,
      "y": 500.0,
      "zoom": 4.6
    },
    {
      "tick": 333,
      "x": 650.0,
      "y": 500.0,
      "zoom": 4.6
    },
    {
      "tick": 336,
      "x": 650.0,
      "y": 500.0,
      "zoom": 4.6
    },
    {
      "tick": 339,
      "x": 650.0,
      "y": 500.0,
      "zoom": 4.6
    },
    {
      "tick": 342,
      "x": 650.0,
      "y": 500.0,
      "zoom": 4.6
    },
    {
      "tick": 345,
      "x": 650.0,
      "y": 500.0,
      "zoom": 4.6
    },
    {
      "tick": 348,
      "x": 650.0,
      "y": 500.0,
      "zoom": 4.6
    },
    {
      "tick": 351,
      "x": 650.0,
      "y": 500.0,
      "zoom": 4.6
    },
    {
      "tick": 354,
      "x": 650.0,
      "y": 500.0,
      "zoom": 4.6
    },
    {
      "tick": 357,
      "x": 650.0,
      "y": 500.0,
      "zoom": 4.6
    },
    {
      "tick": 360,
      "x": 650.0,
      "y": 500.0,
      "zoom": 4.6
    },
    {
      "tick": 363,
      "x": 650.0,
      "y": 500.0,
      "zoom": 4.6
    },
    {
      "tick": 366,
      "x": 650.0,
      "y": 500.0,
      "zoom": 4.6
    },
    {
      "tick": 369,
      "x": 650.0,
      "y": 500.0,
      "zoom": 4.6
    },
    {
      "tick": 372,
      "x": 650.0,
      "y": 500.0,
      "zoom": 4.6
    },
    {
      "tick": 375,
      "x": 650.0,
      "y": 500.0,
      "zoom": 4.6
    },
    {
      "tick": 378,
      "x": 650.0,
      "y": 500.0,
      "zoom": 4.6
    },
    {
      "tick": 381,
      "x": 650.0,
      "y": 500.0,
      "zoom": 4.6
    },
    {
      "tick": 384,
      "x": 650.0,
      "y": 500.0,
      "zoom": 4.6
    },
    {
      "tick": 387,
      "x": 650.0,
      "y": 500.0,
      "zoom": 4.6
    },
    {
      "tick": 390,
      "x": 650.0,
      "y": 500.0,
      "zoom": 4.6
    },
    {
      "tick": 393,
      "x": 650.0,
      "y": 500.0,
      "zoom": 4.6
    },
    {
      "tick": 396,
      "x": 650.0,
      "y": 500.0,
      "zoom": 4.6
    },
    {
      "tick": 399,
      "x": 650.0,
      "y": 500.0,
      "zoom": 4.6
    },
    {
      "tick": 402,
      "x": 650.0,
      "y": 500.0,
      "zoom": 4.6
    },
    {
      "tick": 405,
      "x": 650.0,
      "y": 500.0,
      "zoom": 4.6
    },
    {
      "tick": 408,
      "x": 650.0,
      "y": 500.0,
      "zoom": 4.6
    },
    {
      "tick": 411,
      "x": 650.0,
      "y": 500.0,
      "zoom": 4.6
    },
    {
      "tick": 414,
      "x": 650.0,
      "y": 500.0,
      "zoom": 4.6
    },
    {
      "tick": 417,
      "x": 650.0,
      "y": 500.0,
      "zoom": 4.6
    },
    {
      "tick": 420,
      "x": 650.0,
      "y": 500.0,
      "zoom": 4.6
    },
    {
      "tick": 423,
      "x": 650.0,
      "y": 500.0,
      "zoom": 4.6
    },
    {
      "tick": 426,
      "x": 650.0,
      "y": 500.0,
      "zoom": 4.6
    },
    {
      "tick": 429,
      "x": 650.0,
      "y": 500.0,
      "zoom": 4.6
    },
    {
      "tick": 432,
      "x": 650.0,
      "y": 500.0,
      "zoom": 4.6
    },
    {
      "tick": 435,
      "x": 650.0,
      "y": 500.0,
      "zoom": 4.6
    },
    {
      "tick": 438,
      "x": 650.0,
      "y": 500.0,
      "zoom": 4.6
    },
    {
      "tick": 441,
      "x": 650.0,
      "y": 500.0,
      "zoom": 4.6
    },
    {
      "tick": 444,
      "x": 650.0,
      "y": 500.0,
      "zoom": 4.6
    },
    {
      "tick": 447,
      "x": 650.0,
      "y": 500.0,
      "zoom": 4.6
    },
    {
      "tick": 450,
      "x": 650.0,
      "y": 500.0,
      "zoom": 4.6
    },
    {
      "tick": 453,
      "x": 650.0,
      "y": 500.0,
      "zoom": 4.6
    },
    {
      "tick": 456,
      "x": 650.0,
      "y": 500.0,
      "zoom": 4.6
    },
    {
      "tick": 459,
      "x": 650.0,
      "y": 500.0,
      "zoom": 4.6
    },
    {
      "tick": 462,
      "x": 650.0,
      "y": 500.0,
      "zoom": 4.6
    },
    {
      "tick": 465,
      "x": 650.0,
      "y": 500.0,
      "zoom": 4.6
    },
    {
      "tick": 468,
      "x": 650.0,
      "y": 500.0,
      "zoom": 4.6
    },
    {
      "tick": 471,
      "x": 650.0,
      "y": 500.0,
      "zoom": 4.6
    },
    {
      "tick": 474,
      "x": 650.0,
      "y": 500.0,
      "zoom": 4.6
    },
    {
      "tick": 477,
      "x": 650.0,
      "y": 500.0,
      "zoom": 4.6
    },
    {
      "tick": 480,
      "x": 650.0,
      "y": 500.0,
      "zoom": 4.6
    },
    {
      "tick": 483,
      "x": 650.0,
      "y": 500.0,
      "zoom": 4.6
    },
    {
      "tick": 486,
      "x": 650.0,
      "y": 500.0,
      "zoom": 4.6
    },
    {
      "tick": 489,
      "x": 650.0,
      "y": 500.0,
      "zoom": 4.6
    },
    {
      "tick": 492,
      "x": 650.0,
      "y": 500.0,
      "zoom": 4.6
    },
    {
      "tick": 495,
      "x": 650.0,
      "y": 500.0,
      "zoom": 4.6
    },
    {
      "tick": 498,
      "x": 650.0,
      "y": 500.0,
      "zoom": 4.6
    },
    {
      "tick": 501,
      "x": 650.0,
      "y": 500.0,
      "zoom": 4.6
    },
    {
      "tick": 504,
      "x": 650.0,
      "y": 500.0,
      "zoom": 4.6
    },
    {
      "tick": 507,
      "x": 650.0,
      "y": 500.0,
      "zoom": 4.6
    },
    {
      "tick": 510,
      "x": 650.0,
      "y": 500.0,
      "zoom": 4.6
    },
    {
      "tick": 513,
      "x": 650.0,
      "y": 500.0,
      "zoom": 4.6
    },
    {
      "tick": 516,
      "x": 650.0,
      "y": 500.0,
      "zoom": 4.6
    },
    {
      "tick": 519,
      "x": 650.0,
      "y": 500.0,
      "zoom": 4.6
    },
    {
      "tick": 522,
      "x": 650.0,
      "y": 500.0,
      "zoom": 4.6
    },
    {
      "tick": 525,
      "x": 650.0,
      "y": 500.0,
      "zoom": 4.6
    },
    {
      "tick": 528,
      "x": 650.0,
      "y": 500.0,
      "zoom": 4.6
    },
    {
      "tick": 531,
      "x": 650.0,
      "y": 500.0,
      "zoom": 4.6
    },
    {
      "tick": 534,
      "x": 650.0,
      "y": 500.0,
      "zoom": 4.6
    },
    {
      "tick": 537,
      "x": 650.0,
      "y": 500.0,
      "zoom": 4.6
    },
    {
      "tick": 540,
      "x": 650.0,
      "y": 500.0,
      "zoom": 4.6
    },
    {
      "tick": 543,
      "x": 650.0,
      "y": 500.0,
      "zoom": 4.6
    },
    {
      "tick": 546,
      "x": 650.0,
      "y": 500.0,
      "zoom": 4.6
    },
    {
      "tick": 549,
      "x": 650.0,
      "y": 500.0,
      "zoom": 4.6
    },
    {
      "tick": 552,
      "x": 650.0,
      "y": 500.0,
      "zoom": 4.6
    },
    {
      "tick": 555,
      "x": 650.0,
      "y": 500.0,
      "zoom": 4.6
    },
    {
      "tick": 558,
      "x": 650.0,
      "y": 500.0,
      "zoom": 4.6
    },
    {
      "tick": 561,
      "x": 650.0,
      "y": 500.0,
      "zoom": 4.6
    },
    {
      "tick": 564,
      "x": 650.0,
      "y": 500.0,
      "zoom": 4.6
    },
    {
      "tick": 567,
      "x": 650.0,
      "y": 500.0,
      "zoom": 4.6
    },
    {
      "tick": 570,
      "x": 650.0,
      "y": 500.0,
      "zoom": 4.6
    },
    {
      "tick": 573,
      "x": 650.0,
      "y": 500.0,
      "zoom": 4.6
    },
    {
      "tick": 576,
      "x": 650.0,
      "y": 500.0,
      "zoom": 4.6
    },
    {
      "tick": 579,
      "x": 650.0,
      "y": 500.0,
      "zoom": 4.6
    },
    {
      "tick": 582,
      "x": 650.0,
      "y": 500.0,
      "zoom": 4.6
    },
    {
      "tick": 585,
      "x": 650.0,
      "y": 500.0,
      "zoom": 4.6
    },
    {
      "tick": 588,
      "x": 650.0,
      "y": 500.0,
      "zoom": 4.6
    },
    {
      "tick": 591,
      "x": 650.0,
      "y": 500.0,
      "zoom": 4.6
    },
    {
      "tick": 594,
      "x": 650.0,
      "y": 500.0,
      "zoom": 4.6
    },
    {
      "tick": 597,
      "x": 650.0,
      "y": 500.0,
      "zoom": 4.6
    },
    {
      "tick": 600,
      "x": 650.0,
      "y": 500.0,
      "zoom": 4.6
    },
    {
      "tick": 603,
      "x": 650.0,
      "y": 500.0,
      "zoom": 4.6
    },
    {
      "tick": 606,
      "x": 650.0,
      "y": 500.0,
      "zoom": 4.6
    },
    {
      "tick": 609,
      "x": 650.0,
      "y": 500.0,
      "zoom": 4.6
    },
    {
      "tick": 612,
      "x": 650.0,
      "y": 500.0,
      "zoom": 4.6
    },
    {
      "tick": 615,
      "x": 650.0,
      "y": 500.0,
      "zoom": 4.6
    },
    {
      "tick": 618,
      "x": 650.0,
      "y": 500.0,
      "zoom": 4.6
    },
    {
      "tick": 621,
      "x": 650.0,
      "y": 500.0,
      "zoom": 4.6
    },
    {
      "tick": 624,
      "x": 650.0,
      "y": 500.0,
      "zoom": 4.6
    },
    {
      "tick": 627,
      "x": 650.0,
      "y": 500.0,
      "zoom": 4.6
    },
    {
      "tick": 630,
      "x": 650.0,
      "y": 500.0,
      "zoom": 4.6
    },
    {
      "tick": 633,
      "x": 650.0,
      "y": 500.0,
      "zoom": 4.6
    },
    {
      "tick": 636,
      "x": 650.0,
      "y": 500.0,
      "zoom": 4.6
    },
    {
      "tick": 639,
      "x": 650.0,
      "y": 500.0,
      "zoom": 4.6
    },
    {
      "tick": 642,
      "x": 650.0,
      "y": 500.0,
      "zoom": 4.6
    },
    {
      "tick": 645,
      "x": 650.0,
      "y": 500.0,
      "zoom": 4.6
    },
    {
      "tick": 648,
      "x": 650.0,
      "y": 500.0,
      "zoom": 4.6
    },
    {
      "tick": 651,
      "x": 650.0,
      "y": 500.0,
      "zoom": 4.6
    },
    {
      "tick": 654,
      "x": 650.0,
      "y": 500.0,
      "zoom": 4.6
    },
    {
      "tick": 657,
      "x": 650.0,
      "y": 500.0,
      "zoom": 4.6
    },
    {
      "tick": 660,
      "x": 650.0,
      "y": 500.0,
      "zoom": 4.6
    },
    {
      "tick": 663,
      "x": 650.0,
      "y": 500.0,
      "zoom": 4.6
    },
    {
      "tick": 666,
      "x": 650.0,
      "y": 500.0,
      "zoom": 4.6
    },
    {
      "tick": 669,
      "x": 650.0,
      "y": 500.0,
      "zoom": 4.6
    },
    {
      "tick": 672,
      "x": 650.0,
      "y": 500.0,
      "zoom": 4.6
    },
    {
      "tick": 675,
      "x": 650.0,
      "y": 500.0,
      "zoom": 4.6
    },
    {
      "tick": 678,
      "x": 650.0,
      "y": 500.0,
      "zoom": 4.6
    },
    {
      "tick": 681,
      "x": 650.0,
      "y": 500.0,
      "zoom": 4.6
    },
    {
      "tick": 684,
      "x": 650.0,
      "y": 500.0,
      "zoom": 4.6
    },
    {
      "tick": 687,
      "x": 650.0,
      "y": 500.0,
      "zoom": 4.6
    },
    {
      "tick": 690,
      "x": 650.0,
      "y": 500.0,
      "zoom": 4.6
    },
    {
      "tick": 693,
      "x": 650.0,
      "y": 500.0,
      "zoom": 4.6
    },
    {
      "tick": 696,
      "x": 650.0,
      "y": 500.0,
      "zoom": 4.6
    },
    {
      "tick": 699,
      "x": 650.0,
      "y": 500.0,
      "zoom": 4.6
    }
  ]
}
